cldfcatalog/__init__.py
cldfcatalog/catalog.py
cldfcatalog/config.py
cldfcatalog/repository.py
cldfcatalog-1.6.0.dist-info/LICENSE
cldfcatalog-1.6.0.dist-info/METADATA
cldfcatalog-1.6.0.dist-info/WHEEL
cldfcatalog-1.6.0.dist-info/top_level.txt
cldfcatalog-1.6.0.dist-info/RECORD
