Metadata-Version: 2.1
Name: cldfcatalog
Version: 1.6.0
Summary: A Python library to access CLDF reference catalogs
Home-page: https://github.com/cldf/cldfcatalog
Author: Robert Forkel
Author-email: robert_forkel@eva.mpg.de
License: Apache 2.0
Project-URL: Bug Tracker, https://github.com/cldf/cldfcatalog/issues
Keywords: linguistics
Platform: any
Classifier: Development Status :: 5 - Production/Stable
Classifier: Intended Audience :: Developers
Classifier: Intended Audience :: Science/Research
Classifier: Natural Language :: English
Classifier: Operating System :: OS Independent
Classifier: Programming Language :: Python :: 3
Classifier: Programming Language :: Python :: 3.8
Classifier: Programming Language :: Python :: 3.9
Classifier: Programming Language :: Python :: 3.10
Classifier: Programming Language :: Python :: 3.11
Classifier: Programming Language :: Python :: 3.12
Classifier: Programming Language :: Python :: 3.13
Classifier: Programming Language :: Python :: Implementation :: CPython
Classifier: Programming Language :: Python :: Implementation :: PyPy
Classifier: License :: OSI Approved :: Apache Software License
Requires-Python: >=3.8
License-File: LICENSE
Requires-Dist: pycldf>=1.24
Requires-Dist: gitpython
Requires-Dist: platformdirs
Provides-Extra: dev
Requires-Dist: tox; extra == "dev"
Requires-Dist: flake8; extra == "dev"
Requires-Dist: wheel>=0.36; extra == "dev"
Requires-Dist: twine; extra == "dev"
Provides-Extra: test
Requires-Dist: pytest>=5; extra == "test"
Requires-Dist: pytest-mock; extra == "test"
Requires-Dist: pytest-cov; extra == "test"
